config/__init__.py
config/cnn_config.py
config/config.py
iget_config-1.0.0.dist-info/METADATA
iget_config-1.0.0.dist-info/WHEEL
iget_config-1.0.0.dist-info/top_level.txt
iget_config-1.0.0.dist-info/RECORD
