Metadata-Version: 2.4
Name: iget-config
Version: 1.0.0
Summary: 一个为 PyTorch 项目设计的直观的配置管理库。它通过简单的 YAML 文件实现层级化配置，支持 TEST, DEV, PROD 等多种运行模式，并可通过类继承方便地扩展。让管理不同环境和实验的配置变得轻松。 (注意：作为库使用时，请确保运行目录下存在 `temp/mode.txt` 文件和包含 YAML 文件的 `config` 目录以符合当前加载逻辑)。
Author-email: bdj <byx945@gmail.com>
Project-URL: Homepage, https://github.com/by90
Project-URL: Bug Tracker, https://github.com/by90
Classifier: Programming Language :: Python :: 3
Classifier: License :: OSI Approved :: MIT License
Classifier: Operating System :: OS Independent
Classifier: Topic :: Software Development :: Libraries :: Python Modules
Classifier: Intended Audience :: Developers
Classifier: Natural Language :: Chinese (Simplified)
Requires-Python: >=3.8
Requires-Dist: pyyaml>=5.4
Requires-Dist: torch>=1.8
